jockbot_mlb/__init__.py
jockbot_mlb/config.json
jockbot_mlb/mlb.py
jockbot_mlb-0.6.dist-info/LICENSE
jockbot_mlb-0.6.dist-info/METADATA
jockbot_mlb-0.6.dist-info/WHEEL
jockbot_mlb-0.6.dist-info/top_level.txt
jockbot_mlb-0.6.dist-info/RECORD
