Metadata-Version: 2.1
Name: jockbot-mlb
Version: 0.6
Summary: Retrieve info from MLB API
Home-page: http://github.com/jalgraves/jockbot_mlb
Author: Jonny Graves
Author-email: jal@jalgraves.com
License: MIT
Platform: UNKNOWN
Requires-Dist: aiohttp
Requires-Dist: python-dateutil
